Workbook

Sheet Deal Request Form
A1: Commercial Deal Request Form
A2: Fill only yellow user-input fields. Requested Total Discount % is the complete customer-facing discount from Gross Price. Base Rebate is reference data and is already reflected in Gross Price.
A4: Deal Header
A5: Deal Title | B5: Northstar Commercial Agreement | E5: Deal Type | F5: Contract Renewal | H5: Status | I5: Draft
A6: Sold-To Customer | B6: Northstar Health Systems | E6: End Account | F6: Northstar Health Systems | I6: Commercial Decision Deadline | J6: 46234
A7: Payment Terms | B7: Net 60 | D7: Contract Duration Months | E7: 24 | G7: Billing Frequency | H7: Annual | J7: Special Terms Requested | K7: No
A8: Sales Owner | B8: Maya Chen | E8: Sales Manager | F8: Jordan Blake
A10: Business Justification (Mandatory) | B10: Contract renewal protects strategic volume following competitor entry and supports a commercially sustainable account relationship.
A13: Special Terms Description (Optional)
A16: Line Items
A17: Line # | B17: SKU | C17: Product Name | D17: Quantity | E17: Gross Price | F17: Base Rebate % (Reference) | G17: Current Net Price | H17: Requested Total Discount % | I17: Requested Net Price | J17: Requested Net Revenue | K17: Line Commercial Justification
A18: =IF(B18="","",ROW()-17) -> 1 | B18: RX-ONC-100 | C18: =IFERROR(VLOOKUP(B18,'Reference Data'!$A$2:$F$15,2,FALSE),"") -> Product Alpha | D18: 100 | E18: =IFERROR(VLOOKUP(B18,'Reference Data'!$A$2:$F$15,3,FALSE),"") -> 1776 | F18: =IFERROR(VLOOKUP(B18,'Reference Data'!$A$2:$F$15,4,FALSE),"") -> 0.04 | G18: =IFERROR(VLOOKUP(B18,'Reference Data'!$A$2:$F$15,5,FALSE),"") -> 1776 | H18: 0.09 | I18: =IF(OR(E18="",H18=""),"",E18*(1-H18)) -> 1616.16 | J18: =IF(OR(D18="",I18=""),"",D18*I18) -> 161616 | K18: Total discount supports renewal defense while preserving committed annual volume.
A19: =IF(B19="","",ROW()-17) -> 2 | B19: RX-ONC-500 | C19: =IFERROR(VLOOKUP(B19,'Reference Data'!$A$2:$F$15,2,FALSE),"") -> Product Beta | D19: 25 | E19: =IFERROR(VLOOKUP(B19,'Reference Data'!$A$2:$F$15,3,FALSE),"") -> 6840 | F19: =IFERROR(VLOOKUP(B19,'Reference Data'!$A$2:$F$15,4,FALSE),"") -> 0.05 | G19: =IFERROR(VLOOKUP(B19,'Reference Data'!$A$2:$F$15,5,FALSE),"") -> 6840 | H19: 0.13 | I19: =IF(OR(E19="",H19=""),"",E19*(1-H19)) -> 5950.8 | J19: =IF(OR(D19="",I19=""),"",D19*I19) -> 148770 | K19: Requested total discount reflects competitive pressure and the consolidated contract term.
A20: =IF(B20="","",ROW()-17) | C20: =IFERROR(VLOOKUP(B20,'Reference Data'!$A$2:$F$15,2,FALSE),"") | E20: =IFERROR(VLOOKUP(B20,'Reference Data'!$A$2:$F$15,3,FALSE),"") | F20: =IFERROR(VLOOKUP(B20,'Reference Data'!$A$2:$F$15,4,FALSE),"") | G20: =IFERROR(VLOOKUP(B20,'Reference Data'!$A$2:$F$15,5,FALSE),"") | I20: =IF(OR(E20="",H20=""),"",E20*(1-H20)) | J20: =IF(OR(D20="",I20=""),"",D20*I20)
A21: =IF(B21="","",ROW()-17) | C21: =IFERROR(VLOOKUP(B21,'Reference Data'!$A$2:$F$15,2,FALSE),"") | E21: =IFERROR(VLOOKUP(B21,'Reference Data'!$A$2:$F$15,3,FALSE),"") | F21: =IFERROR(VLOOKUP(B21,'Reference Data'!$A$2:$F$15,4,FALSE),"") | G21: =IFERROR(VLOOKUP(B21,'Reference Data'!$A$2:$F$15,5,FALSE),"") | I21: =IF(OR(E21="",H21=""),"",E21*(1-H21)) | J21: =IF(OR(D21="",I21=""),"",D21*I21)
A22: =IF(B22="","",ROW()-17) | C22: =IFERROR(VLOOKUP(B22,'Reference Data'!$A$2:$F$15,2,FALSE),"") | E22: =IFERROR(VLOOKUP(B22,'Reference Data'!$A$2:$F$15,3,FALSE),"") | F22: =IFERROR(VLOOKUP(B22,'Reference Data'!$A$2:$F$15,4,FALSE),"") | G22: =IFERROR(VLOOKUP(B22,'Reference Data'!$A$2:$F$15,5,FALSE),"") | I22: =IF(OR(E22="",H22=""),"",E22*(1-H22)) | J22: =IF(OR(D22="",I22=""),"",D22*I22)
A23: =IF(B23="","",ROW()-17) | C23: =IFERROR(VLOOKUP(B23,'Reference Data'!$A$2:$F$15,2,FALSE),"") | E23: =IFERROR(VLOOKUP(B23,'Reference Data'!$A$2:$F$15,3,FALSE),"") | F23: =IFERROR(VLOOKUP(B23,'Reference Data'!$A$2:$F$15,4,FALSE),"") | G23: =IFERROR(VLOOKUP(B23,'Reference Data'!$A$2:$F$15,5,FALSE),"") | I23: =IF(OR(E23="",H23=""),"",E23*(1-H23)) | J23: =IF(OR(D23="",I23=""),"",D23*I23)
A24: =IF(B24="","",ROW()-17) | C24: =IFERROR(VLOOKUP(B24,'Reference Data'!$A$2:$F$15,2,FALSE),"") | E24: =IFERROR(VLOOKUP(B24,'Reference Data'!$A$2:$F$15,3,FALSE),"") | F24: =IFERROR(VLOOKUP(B24,'Reference Data'!$A$2:$F$15,4,FALSE),"") | G24: =IFERROR(VLOOKUP(B24,'Reference Data'!$A$2:$F$15,5,FALSE),"") | I24: =IF(OR(E24="",H24=""),"",E24*(1-H24)) | J24: =IF(OR(D24="",I24=""),"",D24*I24)
A25: =IF(B25="","",ROW()-17) | C25: =IFERROR(VLOOKUP(B25,'Reference Data'!$A$2:$F$15,2,FALSE),"") | E25: =IFERROR(VLOOKUP(B25,'Reference Data'!$A$2:$F$15,3,FALSE),"") | F25: =IFERROR(VLOOKUP(B25,'Reference Data'!$A$2:$F$15,4,FALSE),"") | G25: =IFERROR(VLOOKUP(B25,'Reference Data'!$A$2:$F$15,5,FALSE),"") | I25: =IF(OR(E25="",H25=""),"",E25*(1-H25)) | J25: =IF(OR(D25="",I25=""),"",D25*I25)
A26: =IF(B26="","",ROW()-17) | C26: =IFERROR(VLOOKUP(B26,'Reference Data'!$A$2:$F$15,2,FALSE),"") | E26: =IFERROR(VLOOKUP(B26,'Reference Data'!$A$2:$F$15,3,FALSE),"") | F26: =IFERROR(VLOOKUP(B26,'Reference Data'!$A$2:$F$15,4,FALSE),"") | G26: =IFERROR(VLOOKUP(B26,'Reference Data'!$A$2:$F$15,5,FALSE),"") | I26: =IF(OR(E26="",H26=""),"",E26*(1-H26)) | J26: =IF(OR(D26="",I26=""),"",D26*I26)
A27: =IF(B27="","",ROW()-17) | C27: =IFERROR(VLOOKUP(B27,'Reference Data'!$A$2:$F$15,2,FALSE),"") | E27: =IFERROR(VLOOKUP(B27,'Reference Data'!$A$2:$F$15,3,FALSE),"") | F27: =IFERROR(VLOOKUP(B27,'Reference Data'!$A$2:$F$15,4,FALSE),"") | G27: =IFERROR(VLOOKUP(B27,'Reference Data'!$A$2:$F$15,5,FALSE),"") | I27: =IF(OR(E27="",H27=""),"",E27*(1-H27)) | J27: =IF(OR(D27="",I27=""),"",D27*I27)
A29: Calculated Summary
A30: Gross Revenue | B30: =SUMPRODUCT(D18:D27,E18:E27) -> 348600 | D30: Requested Net Revenue | E30: =SUM(J18:J27) -> 310386 | G30: Discount Amount | H30: =B30-E30 -> 38214
A31: Discount % | B31: =IF(B30=0,0,H30/B30) -> 0.10962134 | D31: Gross Profit | E31: =E30-(D18*IFERROR(VLOOKUP(B18,'Reference Data'!$A$2:$F$15,6,FALSE),0)+D19*IFERROR(VLOOKUP(B19,'Reference Data'!$A$2:$F$15,6,FALSE),0)+D20*IFERROR(VLOOKUP(B20,'Reference Data'!$A$2:$F$15,6,FALSE),0)+D21*IFERROR(VLOOKUP(B21,'Reference Data'!$A$2:$F$15,6,FALSE),0)+D22*IFERROR(VLOOKUP(B22,'Reference Data'!$A$2:$F$15,6,FALSE),0)+D23*IFERROR(VLOOKUP(B23,'Reference Data'!$A$2:$F$15,6,FALSE),0)+D24*IFERROR(VLOOKUP(B24,'Reference Data'!$A$2:$F$15,6,FALSE),0)+D25*IFERROR(VLOOKUP(B25,'Reference Data'!$A$2:$F$15,6,FALSE),0)+D26*IFERROR(VLOOKUP(B26,'Reference Data'!$A$2:$F$15,6,FALSE),0)+D27*IFERROR(VLOOKUP(B27,'Reference Data'!$A$2:$F$15,6,FALSE),0)) -> 200886 | G31: Gross Margin % | H31: =IF(E30=0,0,E31/E30) -> 0.64721347
A32: Line Item Count | B32: =COUNTIF(B18:B27,"<>") -> 2 | D32: Submission Readiness | E32: =IF(AND(B5<>"",F5<>"",I5<>"",B6<>"",F6<>"",J6<>"",B7<>"",E7>0,H7<>"",K7<>"",B8<>"",F8<>"",B10<>"",COUNTIF(B18:B27,"<>")>0),"Ready to Submit","Incomplete") -> Ready to Submit
A35: Instructions
A36: 1. Fill only yellow user-input fields. 2. Reference-driven fields are populated from master data. 3. Review the calculated summary before submitting. 4. Business Justification is mandatory; Special Terms Description is optional.

Sheet Validation Lists
A1: Validation Lists
A3: Deal Types | B3: Statuses | C3: Payment Terms | D3: Billing Frequencies | E3: Yes / No | F3: Threat Level
A4: New Account / Launch | B4: Draft | C4: Net 30 | D4: Annual | E4: Yes | F4: Low
A5: Contract Renewal | B5: Submitted | C5: Net 45 | D5: Quarterly | E5: No | F5: Medium
A6: Tender | B6: Changes Requested | C6: Net 60 | D6: Monthly | F6: High
A7: Competitive Defense | B7: Approved | C7: Net 90 | D7: Milestone
A8: Strategic Exception | B8: Rejected | C8: Custom

Sheet Reference Data
A1: Reference Data
A2: SKU | B2: Product Name | C2: Gross Price | D2: Base Rebate % | E2: Current Net Price | F2: Standard Cost | H2: Customers | I2: Sales Owners | J2: Sales Managers
A3: RX-ONC-100 | B3: Product Alpha | C3: 1776 | D3: 0.04 | E3: =C3 -> 1776 | F3: 555 | H3: Northstar Health Systems | I3: Maya Chen | J3: Jordan Blake
A4: RX-ONC-500 | B4: Product Beta | C4: 6840 | D4: 0.05 | E4: =C4 -> 6840 | F4: 2160 | H4: Meridian Specialty Pharmacy | I4: Ethan Brooks
A5: BIO-RA-200 | B5: Product Gamma | C5: 1121 | D5: 0.05 | E5: =C5 -> 1121 | F5: 413 | H5: Apex National GPO
A6: RX-CARD-50 | B6: Product Delta | C6: 394.8 | D6: 0.06 | E6: =C6 -> 394.8 | F6: 147 | H6: HelioRx Distribution
A7: RX-RARE-10 | B7: Product Epsilon | C7: 27170 | D7: 0.05 | E7: =C7 -> 27170 | F7: 7150 | H7: Summit Oncology Clinics
A8: DX-COMP-01 | B8: Product Zeta | C8: 902.5 | D8: 0.05 | E8: =C8 -> 902.5 | F8: 333 | H8: Cityline Payer Alliance
A9: RX-HOSP-20 | B9: Product Eta | C9: 1240.8 | D9: 0.06 | E9: =C9 -> 1240.8 | F9: 462 | H9: Orion Hospital Trust
A10: BIO-DERM-80 | B10: Product Theta | C10: 931 | D10: 0.05 | E10: =C10 -> 931 | F10: 343 | H10: Beacon Clinical Research
A11: RX-ONC-ORAL | B11: Product Iota | C11: 9024 | D11: 0.04 | E11: =C11 -> 9024 | F11: 2820 | H11: Crescent Public Tender Authority
A12: RX-RARE-INF | B12: Product Kappa | C12: 33060 | D12: 0.05 | E12: =C12 -> 33060 | F12: 8700 | H12: Valence Integrated Care
A13: DX-GENE-02 | B13: Product Lambda | C13: 1216 | D13: 0.05 | E13: =C13 -> 1216 | F13: 448 | H13: Harbor Specialty Rx
A14: SVC-PAT-01 | B14: Product Mu | C14: 42000 | D14: 0 | E14: =C14 -> 42000 | F14: 16800 | H14: Union National Payer
A15: SVC-START | B15: Product Nu | C15: 35000 | D15: 0 | E15: =C15 -> 35000 | F15: 14000 | H15: Atlas Hospital Network
A16: REB-FORM | B16: Product Xi | C16: 0 | D16: 0 | E16: =C16 -> 0 | F16: 0 | H16: NovaCare Oncology
H17: Pioneer Medical Group
H18: Europa Health Purchasing
H19: Redwood Regional IDN
H20: Sterling Specialty Distribution
H21: BluePeak Payer Coalition
H22: Metro Infusion Partners
